{
  "@context": [
    "https://linkedsoftwaredependencies.org/bundles/npm/@solid/community-server/^8.0.0/components/context.jsonld",
    "https://linkedsoftwaredependencies.org/bundles/npm/@solidlab/uma-css/^0.0.0/components/context.jsonld"
  ],
  "@graph": [
    {
      "comment": "Provides utility for interacting with pod owner metadata",
      "@id": "urn:solid-server:default:OwnerUtil",
      "@type": "OwnerUtil",
      "accountStorage": {
        "@id": "urn:solid-server:default:AccountStorage"
      },
      "accountStore": {
        "@id": "urn:solid-server:default:AccountStore"
      },
      "podStore": {
        "@id": "urn:solid-server:default:PodStore"
      },
      "storageStrategy": {
        "@id": "urn:solid-server:default:StorageLocationStrategy"
      }
    }
  ]
}
